MANIFEST.in
README.md
requirements.txt
setup.cfg
setup.py
greeks/__init__.py
greeks/_version.py
greeks.egg-info/PKG-INFO
greeks.egg-info/SOURCES.txt
greeks.egg-info/dependency_links.txt
greeks.egg-info/not-zip-safe
greeks.egg-info/requires.txt
greeks.egg-info/top_level.txt