Metadata-Version: 2.1
Name: greeks
Version: 0.0.1
Summary: Analytics library
Home-page: https://github.com/timkpaine/greeks
Author: Tim Paine
Author-email: timothy.k.paine@gmail.com
License: Apache 2.0
Download-URL: https://github.com/timkpaine/greeks/archive/v0.0.1.tar.gz
Keywords: analytics tools
Platform: UNKNOWN
Classifier: Development Status :: 3 - Alpha
Classifier: Programming Language :: Python :: 3
Classifier: Programming Language :: Python :: 3.3
Classifier: Programming Language :: Python :: 3.4
Classifier: Programming Language :: Python :: 3.5
Classifier: Programming Language :: Python :: 3.6
Classifier: Programming Language :: Python :: 3.7
Provides-Extra: dev
